{"THEMAID":7,"SCHWIERIGID":1,"FRAGEID":1328,"FrageText":{"de":"Welches Verhalten wird als Verweigerung der Alkoholkontrolle gewertet?","en":"Which behaviour is deemed a refusal of the alcohol test?","hr":"Koje ponašanje se smatra odbijanjem kontrole alkoholiziranosti?","sl":"Katera ravnanja se smatrajo kot odklonitev kontrole za vsebnost alkohola v telesu?","tr":"Hangi hareketler, alkol kontrolünü reddetme olarak değerlendirilir?"},"AntwortText":{"de":[{"Text":"Die Weigerung, den Alkomat zu benützen"},{"Text":"Mutwillig verursachte ungültige Versuche mit dem Alkomat"},{"Text":"Das Bestehen auf eine Wartefrist von 15 Minuten nach Konsum von Getränken oder Speisen bzw. dem Rauchen von Tabakwaren"},{"Text":"Die Weigerung, sich einem Amtsarzt vorführen zu lassen"}],"en":[{"Text":"The refusal of taking a breathalyzer test"},{"Text":"Wantonly caused invalid attempts of breathalyzer test"},{"Text":"If the driver insists on a waiting period of 15 minutes after eating or drinking or smoking"},{"Text":"The driver's refusal to appear before a public health officer"}],"hr":[{"Text":"Odbijanje korištenja alkometra"},{"Text":"Namjerno prouzročeni nevažeći pokusi s alkometrom"},{"Text":"Inzistiranje na vremenu čekanja od 15 minuta nakom konzumiranja pića ili jela, odnosno pušenja duhana"},{"Text":"Odbijanje odvođenja službenom liječniku"}],"sl":[{"Text":"Zavrnitev preizkusa z alkomatom"},{"Text":"Samonamerno povzročanje nepravilnih preizkusov z alkomatom"},{"Text":"Vztrajane na čakalnem roku 15 minut po uživanju pijač ali hrane oz.kajenja tobačnih izdelkov"},{"Text":"Zavrnitev strokovnega pregleda pri zdravniku"}],"tr":[{"Text":"Alkomat aletini kullanmayı reddetmek"},{"Text":"Alkomat aletini kasti olarak yanlış kullanmak"},{"Text":"Bir şeyler yiyip içmek ya da bir sigara yakmak için,15 dakikalık bir bekleme istemek"},{"Text":"Görevli bir doktor tarafından muayeneyi reddetmek"}]},"AntwortRichtig":[true,true,false,true],"ZusatzFrage":1327}