{"THEMAID":8,"SCHWIERIGID":2,"FRAGEID":1435,"FrageText":{"de":"Wann dürfen Sie Straßenbahngleise nicht befahren?","en":"When may you not travel on streetcar tracks?","hr":"Kad se tramvajskim tračnicama ne smije voziti?","sl":"Kdaj ne smete prevoziti tirnic cestne železnice?","tr":"Tramvay rayları üzerinden ne zaman gidemezsiniz?"},"AntwortText":{"de":[{"Text":"Wenn die Gleise an beiden Fahrbahnrändern liegen und die übrige Fahrbahn genügend breit ist"},{"Text":"Wenn es sich um einen selbstständigen Gleiskörper handelt"},{"Text":"Wenn die Gleise am rechten Fahrbahnrand liegen"},{"Text":"Wenn ich in einer Einbahnstraße fahre"}],"en":[{"Text":"If the tracks run on both sides of the roadway and the remaining roadway is wide enough"},{"Text":"If the track is separated from the roadway"},{"Text":"If the tracks are on the right-hand side of the roadway"},{"Text":"When I am travelling in a one-way street"}],"hr":[{"Text":"Kad tračnice leže na oba ruba kolnika, a preostali kolnik je dovoljno širok"},{"Text":"Kad se radi o odvojenim tračnicama"},{"Text":"Kad su tračnice na desnom rubu kolnika"},{"Text":"Kad vozim cestom s jednosmjernim prometom"}],"sl":[{"Text":"Če tiri ležijo na obeh robovih vozišča in je ostala prometna površina dovolj široka"},{"Text":"Kadar se tirnice smatrajo za samostojno tirišče"},{"Text":"Kadar so tiri položeni ob desnem robu vozišča"},{"Text":"Kadar vozim po enosmerni cesti"}],"tr":[{"Text":"Raylar yolun her iki kenarındaysa ve geri kalan yol yeterince geniş ise"},{"Text":"Raylar yoldan seviye farkı ile ayrılmışsa"},{"Text":"Raylar yolun sağ kenarındaysalar"},{"Text":"Tek istikametli yolda gidiyorsam"}]},"AntwortRichtig":[true,true,false,false]}