{"THEMAID":11,"SCHWIERIGID":1,"FRAGEID":1500,"FrageText":{"de":"Warum müssen Ölwechsel regelmäßig durchgeführt werden?","en":"Why must the oil be changed at regular intervals?","hr":"Zašto se izmjena ulja mora redovito obavljati?","sl":"Zakaj je potrebno redno menjati olje?","tr":"Yağ değiştirme niçin düzenli olarak yapılmalıdır?"},"AntwortText":{"de":[{"Text":"Weil sonst der Motor zu rosten beginnt"},{"Text":"Weil sonst das Motoröl seine Schmierfähigkeit verliert"},{"Text":"Weil sonst die Öldruckkontrollleuchte aufleuchtet"},{"Text":"Weil sonst mit stark erhöhtem Treibstoffverbrauch zu rechnen ist"}],"en":[{"Text":"Otherwise the engine will begin to get rusty"},{"Text":"Otherwise the motor oil will lose its lubricity"},{"Text":"Otherwise the oil pressure warning light will show red"},{"Text":"One can assume an increased fuel consumption otherwise"}],"hr":[{"Text":"Jer inače motor počinje hrđati"},{"Text":"Jer inače motorno ulje počinje gubiti svoju mazivost"},{"Text":"Jer inače zasvijetli kontrolna žaruljica za tlak ulja"},{"Text":"Jer se inače mora računati sa jako povećanom potrošnjom goriva"}],"sl":[{"Text":"Ker prične motor rjaveti"},{"Text":"Ker motorno olje izgubi mazalno sposobnost"},{"Text":"Ker zasveti kontrolna luč oljnega pritiska"},{"Text":"Ker drugače je treba računati z močno povečano uporabo goriva"}],"tr":[{"Text":"Çünkü motor paslanmaya başlar"},{"Text":"Çünkü motor yağının yağlama özelliği kaybolur"},{"Text":"Çünkü yağ basınç kontrol lambası yanar"},{"Text":"Aksi taktirde aşırı yakıt sarfiyatı söz konusu olabilir"}]},"AntwortRichtig":[false,true,false,false]}