{"THEMAID":11,"SCHWIERIGID":2,"FRAGEID":1501,"FrageText":{"de":"Was sollen Sie als Lenker an den Reifen Ihres Fahrzeuges überprüfen?","en":"As the driver, what should you check on your vehicle's tires?","hr":"Što trebate kao vozač kontrolirati na gumama svoga vozila?","sl":"Kaj morate kot voznik preveriti na pnevmatikah vašega vozila?","tr":"Bir sürücü olarak aracınızın lastiklerinde neyi kontrol etmelisiniz?"},"AntwortText":{"de":[{"Text":"Ich überprüfe den Reifendruck"},{"Text":"Ich überprüfe, ob die Indikatoren richtig angebracht sind"},{"Text":"Ich überprüfe die Profiltiefe"},{"Text":"Ich überprüfe, ob keine äußeren Beschädigungen am Reifen sichtbar sind"}],"en":[{"Text":"I check the tire pressure"},{"Text":"I check if the indicators are correctly mounted"},{"Text":"I check the tread depth"},{"Text":"I check if there is any visible external damage to the tires"}],"hr":[{"Text":"Provjeravam tlak u gumama"},{"Text":"Provjeravam jesu li indikatori nanešeni na pravo mjesto"},{"Text":"Provjeravam dubinu profila"},{"Text":"Provjeravam nisu li vidljiva vanjska oštećenja na gumama"}],"sl":[{"Text":"Preverim pritisk v pnevmatikah"},{"Text":"Preverim, če so indikatorji pravilno nameščeni"},{"Text":"Preverim globino profila"},{"Text":"Preverim, če so vidne zunanje poškodbe pnevmatik"}],"tr":[{"Text":"Hava basıncını"},{"Text":"Indikatörlerin doğru yerde olup olmadıklarını kontrol ederim"},{"Text":"Profil derinliğini kontrol ederim"},{"Text":"Lastiklerin dış tarafında bir hasar olup olmadığını kontrol ederim"}]},"AntwortRichtig":[true,false,true,true],"ZusatzFrage":1502}