{"THEMAID":53,"SCHWIERIGID":3,"FRAGEID":1563,"FrageText":{"de":"Sie haben auf einer unübersichtlichen Stelle einer Freilandstraße eine Panne mit Ihrem PKW. Wie verhalten Sie sich?","en":"Your automobile has broken down on a blind spot on a country road. How do you conduct yourself?","hr":"Na svom osobnom automobilu imate kvar na nepreglednom mjestu ceste izvan naselja. Kako postupate?","sl":"Na nepregledanem delu vozišča izven naselja imate okvaro na osebnem vozilu. Kaj boste storili?","tr":"Şehir dışında önü görünmeyen bir yerde aracınız arızalandı. Nasıl davranırsınız?"},"AntwortText":{"de":[{"Text":"Ich muss die Alarmblinkanlage einschalten"},{"Text":"Ich muss ein Pannendreieck aufstellen"},{"Text":"Ich muss für die ehestmögliche Entfernung des Fahrzeuges Sorge tragen"},{"Text":"Ich muss das Fahrzeug bewachen"}],"en":[{"Text":"I must turn on the hazard lights"},{"Text":"I must put up the warning triangle"},{"Text":"I must ensure that the vehicle is removed as quickly as possible"},{"Text":"I must guard the vehicle"}],"hr":[{"Text":"Moram uključiti sve pokazivače smjera"},{"Text":"Moram postaviti sigurnosni trokut"},{"Text":"Moram se pobrinuti za što brže uklanjanje vozila"},{"Text":"Moram nadzirati vozilo"}],"sl":[{"Text":"Moram vklopiti vse štiri smernike"},{"Text":"Moram postaviti varnostni trikotnik"},{"Text":"Čim prej moram odstraniti vozilo"},{"Text":"Vozilo moram nadzorovati"}],"tr":[{"Text":"Dörtlü sinyallerimi açarım"},{"Text":"Tehlike üçgenini yerleştiririm"},{"Text":"Aracımın en kısa zamanda yoldan uzaklaştırılmasını sağlarım"},{"Text":"Aracıma göz kulak olmalıyım"}]},"AntwortRichtig":[true,true,true,false],"ZusatzFrage":1564}