{"THEMAID":52,"SCHWIERIGID":2,"FRAGEID":1735,"FrageText":{"de":"Welche Hilfsmittel können bei der Überprüfung der Reifen verwendet werden?","en":"What aids can be used when checking the tires?","hr":"Koja se pomoćna sredstva mogu koristiti prilikom provjere guma?","sl":"Katere pripomočke lahko uporabimo pri preizkušanju pnevmatik?","tr":"Lastikleri kontrol ederken, hangi yardımcı araçları kullanabilirsiniz?"},"AntwortText":{"de":[{"Text":"Mit Hilfe eines Manometers wird der Reifendruck gemessen"},{"Text":"Mit Hilfe einer Profiltiefenlehre wird die Profiltiefe gemessen"},{"Text":"Mit Hilfe der Indikatoren wird das Erreichen der Mindestprofiltiefe festgestellt"},{"Text":"Mit Hilfe eines Indikators wird der Reifendruck gemessen"}],"en":[{"Text":"The tire pressure is measured with the help of a manometer"},{"Text":"The tread depth is measured with the help of a tread depth gauge"},{"Text":"The minimum tread depth is determined with the help of indicators"},{"Text":"The tire pressure is measured with the help of an indicator"}],"hr":[{"Text":"Tlak u gumama se mjeri uz pomoć manometra"},{"Text":"Dubina profila se mjeri uz pomoć dubinomjera profila"},{"Text":"Uz pomoć indikatora se utvrđuje kad je dosegnuta najmanja dubina profila"},{"Text":"Tlak u gumama se mjeri uz pomoć indikatora"}],"sl":[{"Text":"S pomočjo manometra preizkusimo tlak v pnevmatikah"},{"Text":"S pomočjo globinske šablone, preizkusimo globino profila"},{"Text":"S pomočjo indikatorjev ugotovimo, če je dosežena minimalna globina profila"},{"Text":"S pomočjo indikatorjev merimo pritisk tlaka v pnevmatiki"}],"tr":[{"Text":"Bir manometre yardımıyla lastik basıncı ölçülür"},{"Text":"Profil derinlik aletiyle, profil derinliği ölçülür"},{"Text":"Indikatörler yardımıyla en az profil derinliğine ulaşılıp ulaşılmadığı tespit edilir"},{"Text":"Indikatör yardımıyla lastik basıncı ölçülür"}]},"AntwortRichtig":[true,true,true,false]}