{"THEMAID":51,"SCHWIERIGID":2,"FRAGEID":2030,"FrageText":{"de":"Für welche Situationen muss die Ladung gesichert werden?","en":"For what situations should teh load be secured?","hr":"U kojim situacijama teret mora biti osiguran?","sl":"Za  katere situacije mora biti tovor zavarovan?","tr":"Yük hangi durumlar için bağlanmalıdır?"},"AntwortText":{"de":[{"Text":"Die Ladung darf bei Notbremsungen nicht wesentlich verrutschen oder kippen"},{"Text":"Die Ladung darf bei scharfen Ausweichmanövern nicht wesentlich verrutschen oder kippen"},{"Text":"Die Ladung darf bei einem Unfall nicht verrutschen"},{"Text":"Nur für Fahrten außerhalb des Ortsgebietes"}],"en":[{"Text":"The load should not slide or tilt significantly when the emergency brakes are applied"},{"Text":"The load should not slide or tilt significantly when sharp avidance manoeuvres are made"},{"Text":"The load should not slide in the event of an accident"},{"Text":"Only for outstation trips"}],"hr":[{"Text":"Teret ne smije klizati ili se iskrenuti pri naglom kočenju"},{"Text":"Teret ne smije klizati ili se iskrenuti pri oštrim zaokretima u vožnji"},{"Text":"Teret se ne smije klizati u slučaju nesreće"},{"Text":"Samo za vozače izvan naseljenog mjesta"}],"sl":[{"Text":"Pri ustavljalnem zaviranju, tovor ne sme bistveno zdrseti ali se prevrniti"},{"Text":"Pri ostrem izogibanju, tovor ne sme bistveno zdrseti ali se prevrniti"},{"Text":"Pri nesreči tovor ne sme zdrsniti"},{"Text":"Le za vožnje izven naselij"}],"tr":[{"Text":"Yük, acil frenleme durumunda önemli ölçüde kaymamalıdır veya devrilmemelidir"},{"Text":"Yük, keskin manevralarda önemli ölçüde kaymamalıdır veya devrilmemelidir"},{"Text":"Yük, bir kaza durumunda kaymamalıdır"},{"Text":"Sadece meskun mahaller dışındaki yollarda sürüş için"}]},"AntwortRichtig":[true,true,false,false]}