{"THEMAID":31,"SCHWIERIGID":2,"FRAGEID":2212,"BildName":"11508Z.jpg","FrageText":{"de":"Sie fahren mit etwa 60 km/h. Das nachfolgende Fahrzeug blinkt links. Wie verhalten Sie sich?","en":"You are driving at 60 km/h You realise that the following vehicle signals left How will you conduct yourself?","hr":"Vozite oko 60 km/h. Vozilo koje dolazi otraga daje lijevi pokazivač smjera. Kako ćete postupiti?","sl":"Peljete se s hitrostjo približno 60 km/h. Za vami vozeče vozilo, je vklopil levi smerni kazalec. Kako boste v dani situaciji ravnali?","tr":"Yaklaşık 60 km/s ile gidiyorsunuz. Takip eden araç sol sinyali veriyor. Nasıl davranırsınız?"},"AntwortText":{"de":[{"Text":"Ich fahre am äußerst rechten Fahrbahnrand"},{"Text":"Ich halte meine Fahrgeschwindigkeit gleich"},{"Text":"Ich muss meine Fahrgeschwindigkeit verringern"},{"Text":"Ich beschleunige"}],"en":[{"Text":"I will drive on the utmost right verge of the road"},{"Text":"I hold my speed constant"},{"Text":"I have to decrease speed"},{"Text":"I will accelerate"}],"hr":[{"Text":"Vozim uz krajnji desni rub kolnika"},{"Text":"Zadržavam svoju brzinu kretanja"},{"Text":"Moram smanjiti svoju brzinu kretanja"},{"Text":"Ubrzavam"}],"sl":[{"Text":"Držim se ob skrajno desnem robu vozišča"},{"Text":"Držim konstantno hitrost vožnje"},{"Text":"Svojo hitrost vožnje moram zmanjšati"},{"Text":"Pospešil bom"}],"tr":[{"Text":"Yolun en sağ kenarından giderim"},{"Text":"Hızımı aynı tutarım"},{"Text":"Hızımı azaltmam gerekir"},{"Text":"Hızlanırım"}]},"AntwortRichtig":[true,true,false,false]}