{"THEMAID":33,"SCHWIERIGID":2,"FRAGEID":2348,"FrageText":{"de":"Wie können Sie am Kurvenausgang das Einfahren in die anschließende Gerade unterstützen?","en":"How can you support the entry to the adjacent straight at the exit of the curve?","hr":"Kako možete na izlasku iz zavoja pomoći prijelaz u ravninu iza zavoja?","sl":"Nahajate se na izhodu ovinka. Kako boste lahko sedaj olajšali svojo nadaljnjo vožnjo, če je cesta pred vami sedaj ravna?","tr":"Viraj çıkışında müteakip olarak gelen düzlüğe girişinizi nasıl destekleyebilirsiniz?"},"AntwortText":{"de":[{"Text":"Ich beschleunige dosiert"},{"Text":"Ich bremse leicht mit der Hinterradbremse"},{"Text":"Ich bremse leicht mit der Vorderradbremse"},{"Text":"Am Kurvenausgang sollte ich bereits wieder im Spurstreifen fahren"}],"en":[{"Text":"I will accelerate moderately"},{"Text":"I will press slightly on the rear brake"},{"Text":"I will press slightly on the front brake"},{"Text":"At the exit of the curve I should be driving in the lane again"}],"hr":[{"Text":"Dozirano ubrzavam"},{"Text":"Lagano kočim kočnicom kotača"},{"Text":"Lagano kočim kočnicom prednjeg kotača"},{"Text":"Na izlasku iz zavoja moram se ponovno vratiti u udubljenje od kotača"}],"sl":[{"Text":"Pospešil bom zmerno"},{"Text":"Lažje bom zaviral z nožno zavoro"},{"Text":"Lažje bom zaviral s sprednjo zavoro"},{"Text":"Na izhodu ovinka, naj bi zopet peljal v svoji vozni sledi"}],"tr":[{"Text":"Ölçülü şekilde hızlanırım"},{"Text":"Arka teker freni ile hafifçe fren yaparım"},{"Text":"Ön teker freni ile hafifçe fren yaparım"},{"Text":"Viraj çıkışında sürüş çizgisinde olmam gerekir"}]},"AntwortRichtig":[true,false,false,true]}