{"THEMAID":30,"SCHWIERIGID":2,"FRAGEID":2422,"FrageText":{"de":"Welche Schutzausrüstung ist zum Lenken eines Motorrades erforderlich?","en":"What kind of protective gear is necessary for driving a motorcycle?","hr":"Koja zaštitna oprema je potrebna za upravljanje motociklom?","sl":"Katera zaščitna oprema je potrebna, da se lahko peljete z motornim kolesom?","tr":"Bir motosikleti kullanabilmek için hangi koruma donanımları gereklidir?"},"AntwortText":{"de":[{"Text":"Im Ortsgebiet benötige ich auf kurzen Strecken keine Schutzausrüstung"},{"Text":"Bei großer Hitze muss ich keinen Sturzhelm tragen"},{"Text":"Ich muss einen Sturzhelm mit Prüfzeichen tragen"},{"Text":"Der Sturzhelm muss unbeschädigt und für meine Kopfgröße passend sein"}],"en":[{"Text":"Within town limits I do not need any protection gear when driving short distances"},{"Text":"I am allowed to drive without wearing a helmet when it is very hot"},{"Text":"I have to wear a helmet with a check sign"},{"Text":"The helmet has to be free of any damages and fitting my size of head"}],"hr":[{"Text":"U naselju, na kratkim dionicma ne treba mi zaštitna oprema"},{"Text":"Na vrućini ne moram nositi zaštitnu kacigu"},{"Text":"Moram nositi zaštitnu kacigu sa kontrolnim znakom"},{"Text":"Zaštitna kaciga mora biti neoštećena i mora odgovarati mojoj veličini glave"}],"sl":[{"Text":"Na kratkih razdaljah v naseljih ne potrebujem zaščitne opreme"},{"Text":"Pri visoki vročini ne potrebujem čelade"},{"Text":"Moram nositi čelado, ki ima oznako, da je testirana"},{"Text":"Čelada mora biti nepoškodovana in primerna za velikost moje glave"}],"tr":[{"Text":"Şehir içindeki kısa mesafelerde koruma donanımına ihtiyacım yok"},{"Text":"Aşırı sıcak havada kask takmak zorunda değilim"},{"Text":"Test edildiğine dair işareti bulunan bir kask takmalıyım"},{"Text":"Kask hasarsız ve kafa büyüklüğüme uygun olmalıdır"}]},"AntwortRichtig":[false,false,true,true]}