{"THEMAID":6,"SCHWIERIGID":2,"FRAGEID":309,"BildName":"10075Z.jpg","FrageText":{"de":"Sie fahren bereits längere Zeit hinter diesem LKW. Plötzlich blinkt er rechts, was kann das bedeuten?","en":"You are driving for a longer period of time behind this truck. The truck suddenly signals right. What can this mean?","hr":"Već duže vrijeme vozite iza ovog teretnog motornog vozila. Odjednom on uključi desni pokazivač smjera. Što to može značiti?","sl":"Že dalj časa vozite za tem tovornim motornim vozilom. Nenadoma vklopi desni smerokaz. Kaj lahko to pomeni?","tr":"Uzun süredir bu kamyonun arkasından gidiyorsunuz. Birden sağa sinyal veriyor. Bu ne anlama gelebilir?"},"AntwortText":{"de":[{"Text":"Er will rückwärts fahren"},{"Text":"Er will anhalten"},{"Text":"Er zeigt eine Überholmöglichkeit an"},{"Text":"Er will den Sicherheitsabstand vergrößern"}],"en":[{"Text":"He wants to drive in reverse"},{"Text":"He wants to stop"},{"Text":"He signals that it is possible to overtake"},{"Text":"He wants to increase the safety distance"}],"hr":[{"Text":"On hoće voziti unatrag"},{"Text":"On se hoće zaustaviti"},{"Text":"Pokazuje mogućnost za pretjecanje"},{"Text":"On hoće povećati sigurnosni razmak"}],"sl":[{"Text":"Želi peljati vzvratno"},{"Text":"Želi ustaviti"},{"Text":"Nakazuje na možnost prehitevanja"},{"Text":"Želi povečati varnostno razdaljo"}],"tr":[{"Text":"Geri geri gelmek istiyor"},{"Text":"Durmak istiyor"},{"Text":"Sollayabilirsin işareti veriyor"},{"Text":"Güvenlik mesafesini açmak istiyor"}]},"AntwortRichtig":[false,true,true,false],"ZusatzFrage":310}