{"THEMAID":30,"SCHWIERIGID":1,"FRAGEID":346,"FrageText":{"de":"Welche empfehlenswerte Bekleidung gibt es für das Motorradfahren?","en":"What clothes are recommended for driving a motorcycle?","hr":"Koja preporučljiva odjeća postoji za vožnju motocikla?","sl":"Katera priporočena oblačila obstajajo za vožnjo z motornim kolesom?","tr":"Motorsiklet sürmek için hangi tür giysiler tavsiye edilir?"},"AntwortText":{"de":[{"Text":"Schutzkleidung aus Leder oder Textilfasern"},{"Text":"Kurzärmelige Jacke"},{"Text":"Regenanzug"},{"Text":"Handschuhe und Stiefel"}],"en":[{"Text":"Protective gear made from leather or fabrics"},{"Text":"Short sleeved jackets"},{"Text":"Rain gear"},{"Text":"Gloves and boots"}],"hr":[{"Text":"Zaštitna odjeća od kože ili tekstilnih vlakana"},{"Text":"Jakna kratkih rukava"},{"Text":"Kišno odijelo"},{"Text":"Rukavice ili čizme"}],"sl":[{"Text":"Zaščitna oblačila iz usnja ali tekstilnih vlaken"},{"Text":"Suknjič s kratkimi rokavi"},{"Text":"Oblačilo za dež"},{"Text":"Rokavice in škornji"}],"tr":[{"Text":"Deri ya da tekstilden koruma giysisi"},{"Text":"Kısa kollu mont"},{"Text":"Yağmurluk"},{"Text":"Eldiven ve çizme"}]},"AntwortRichtig":[true,false,true,true],"ZusatzFrage":347}