{"THEMAID":30,"SCHWIERIGID":2,"FRAGEID":389,"FrageText":{"de":"Welche Gefahren bestehen, wenn sich Ihr Beifahrer in einer Rechtskurve nach links lehnt?","en":"What dangers arise when your passenger leans to the left when in a right curve?","hr":"Koje opasnosti postoje ako se Vaš suvozač u desnom zavoju nagne ulijevo?","sl":"Katere nevarnosti obstajajo, če se sopotnik v desnem oviku, nagne v levo?","tr":"Yanınızda gelen bir kişi sağa doğru virajda sola doğru eğilirse, hangi tehlikeler oluşabilir?"},"AntwortText":{"de":[{"Text":"Mein Bremsweg wird länger"},{"Text":"Das Motorrad richtet sich unkontrolliert aus der Schräglage auf"},{"Text":"Das Motorrad fällt unkontrolliert in noch tiefere Schräglage"},{"Text":"Ich komme von der beabsichtigten Fahrlinie ab"}],"en":[{"Text":"My braking distance becomes longer"},{"Text":"The motorcycle moves uncontrollably out of its slant"},{"Text":"The motorcycle falls uncontrollably into a larger slant"},{"Text":"I come away from my intended driving path"}],"hr":[{"Text":"Put kočenja mi se produžava"},{"Text":"Motocikl se nekontrolirano uspravlja iz kosog položaja"},{"Text":"Motocikl se nekontrolirano još više naginje"},{"Text":"Gubim položaj na prometnoj traci kojom sam najmjeravao voziti"}],"sl":[{"Text":"Zavorna pot se podaljša"},{"Text":"Motorno kolo se nekontrolirano usmeri iz poševnega položaja"},{"Text":"Motorno kolo nekontrolirano pade v še nižji poševni položaj"},{"Text":"Z motornim kolesom lahko zapeljem iz nameravane vozne linije"}],"tr":[{"Text":"Fren yolum uzar"},{"Text":"Motorsiklet, yan yatmışken, kontrolsüz bir şekilde doğrulur"},{"Text":"Motorsiklet, kontrolsüz bir şekilde daha fazla yan yatar"},{"Text":"Gidilen sürüş çizgisinden çıkarım"}]},"AntwortRichtig":[false,true,false,true]}