{"THEMAID":32,"SCHWIERIGID":1,"FRAGEID":526,"FrageText":{"de":"Der Motor Ihres Motorrades ist wassergekühlt. Was haben Sie zu beachten?","en":"The engine of your motorcycle is water-cooled. What must you watch out for?","hr":"Motor Vašeg motocikla ima hlađenje tekućinom. Na što morate obratiti pozornost?","sl":"Motor Vašega motornega kolesa je vodno hlajen. Na kaj morate biti pozorni?","tr":"Motorsikletinizin motoru soğutma suyuyla soğutuluyor. Neye dikkat edersiniz?"},"AntwortText":{"de":[{"Text":"Ich kontrolliere den Kühlmittelstand und fülle gegebenenfalls nach"},{"Text":"Bei jedem Tankstopp muss ich auch Kühlwasser nachfüllen"},{"Text":"Ich vermeide längeres Laufenlassen des Motors bei Stillstand"},{"Text":"Ich reinige den Kühler regelmäßig von Fliegen und Schmutz"}],"en":[{"Text":"I check the coolant level and top up if necessary"},{"Text":"I must top up the coolant at every tank stop"},{"Text":"I avoid letting the engine idle for longer periods of time when stopped"},{"Text":"I regulary clean off the flies and dirt from the radiator"}],"hr":[{"Text":"Kontroliram razinu rashladne tekićine i nadolijem ukoliko je potrebno"},{"Text":"Kod svakog zaustavljanja radi punjenja goriva moram nadoliti tekućinu za hlađenje"},{"Text":"Izbjegavam duži rad motora dok stoji"},{"Text":"Redovito čistim hladnjak od muha i prljavštine"}],"sl":[{"Text":"Redno preverjam nivo hladilne tekočine in ga po možnosti dolivam"},{"Text":"Pri vsakem črpanju goriva moram doliti tudi hladilno tekočino"},{"Text":"Izogibam se daljšega delovanja motorja v prostem teku in to na mestu"},{"Text":"Redno odstranjujem s hladilnika mrčes in umazanijo"}],"tr":[{"Text":"Soğutma suyu seviyesini kontrol eder, icabında doldururum"},{"Text":"Her benzin koyduğumda, soğutma suyuna su eklerim"},{"Text":"Motorsiklet dururken, motorun uzun süre çalışmasından kaçınırım"},{"Text":"Soğutucuyu düzenli olarak sineklerden ve pislikten arındırırım"}]},"AntwortRichtig":[true,false,true,true],"ZusatzFrage":527}