{"THEMAID":13,"SCHWIERIGID":3,"FRAGEID":600,"BildName":"10712Z.jpg","FrageText":{"de":"Dürfen Sie den Heuwagen hier überholen?","en":"Are you permitted to overtake the hay wagon here?","hr":"Smijete li ovdje pretjecati kola sa sijenom?","sl":"Ali smete tukaj prehiteti vozilo, ki prevaža seno?","tr":"Burada saman yüklü arabayı sollayabilir misiniz?"},"AntwortText":{"de":[{"Text":"Nein, da die Sicht auf einen Gegenverkehr verdeckt ist"},{"Text":"Nein, da die Sicht auf einen Rechtskommenden verdeckt ist"},{"Text":"Ja, weil der Heuwagen kein mehrspuriges Kraftfahrzeug ist"},{"Text":"Ja, nur wenn kein Fahrzeug von rechts kommt"}],"en":[{"Text":"No, because I can not see if there is oncoming traffic"},{"Text":"No, because I can not see if a vehicle is coming from the right"},{"Text":"Yes, because the hay wagon is not a multi-track motor vehicle"},{"Text":"Yes, only when there is no vehicle coming from the right"}],"hr":[{"Text":"Ne, budući da je zaklonjen pogled na promet iz suprotnog smjera"},{"Text":"Ne, budući da je zaklonjen pogled na vozilo koje dolazi s desne strane"},{"Text":"Da, budući da kola sa sijenom nisu vozilo na motorni pogon s više tragova"},{"Text":"Da, samo ako ne dolazi nikakvo vozilo s desne strane"}],"sl":[{"Text":"Ne, ker je pogled na nasprotni promet zakrit"},{"Text":"Ne, ker je pogled na vozilo, prihajajoče z desne, zakrit"},{"Text":"Da, ker je vozilo, ki prevaža seno, večsledno vozilo"},{"Text":"Da, če z desne ne prihaja nobeno vozilo"}],"tr":[{"Text":"Hayır, çünkü karşı trafik görüşü engellenmiştir"},{"Text":"Hayır, çünkü sağdan geleni görmek mümkün değildir"},{"Text":"Evet, çünkü saman arabası çok izli bir araç değildir"},{"Text":"Evet, sadece sağdan araç gelmezse"}]},"AntwortRichtig":[false,true,false,false],"ZusatzFrage":601}