{"THEMAID":13,"SCHWIERIGID":3,"FRAGEID":633,"BildName":"10724Z.jpg","FrageText":{"de":"Welche Fahrzeuge dürfen auf dieser Kreuzung nicht überholt werden?","en":"What vehicles are not permitted to be overtaken at this intersection?","hr":"Koja vozila se ne smiju pretjecati na ovom raskrižju?","sl":"Katera vozila v tem križišču ne smem prehiteti?","tr":"Bu kavşakta ne tür araçlar sollanamaz?"},"AntwortText":{"de":[{"Text":"Nur mehrspurige Kraftfahrzeuge"},{"Text":"Ein- und mehrspurige Kraftfahrzeuge"},{"Text":"Alle mehrspurigen Fahrzeuge"},{"Text":"Nur einspurige Kraftfahrzeuge"}],"en":[{"Text":"Only multi-track motor vehicles"},{"Text":"Single- and multi-track motor vehicles"},{"Text":"All multi-track vehicles"},{"Text":"Only single-track motor vehicles"}],"hr":[{"Text":"Samo vozila na motorni pogon s više tragova"},{"Text":"Vozila na motorni pogon s jednim i više tragova"},{"Text":"Sva vozila s više tragova"},{"Text":"Samo vozila na motorni pogon s jednim tragom"}],"sl":[{"Text":"Samo večsledna motorna vozila"},{"Text":"Enosledna in večsledna motorna vozila"},{"Text":"Vsa večsledna vozila"},{"Text":"Samo enosledna motorna vozila"}],"tr":[{"Text":"Sadece çok izli motorlu araçlar"},{"Text":"Tek ve çok izli motorlu araçlar"},{"Text":"Bütün çok izli araçlar"},{"Text":"Sadece tek izli motorlu araçlar"}]},"AntwortRichtig":[false,false,true,false],"ZusatzFrage":634}