{"THEMAID":12,"SCHWIERIGID":1,"FRAGEID":684,"FrageText":{"de":"Welche Voraussetzungen müssen für das Nebeneinanderfahren gegeben sein?","en":"What conditions must exist in order to be permitted to drive next to each other?","hr":"Koje pretpostavke moraju postojati za usporednu vožnju?","sl":"Katere predpostavke so potrebne pri vzporedni vožnjo?","tr":"Yan yana araç kullanabilmek için hangi şartların olması gerekir?"},"AntwortText":{"de":[{"Text":"Es müssen mindestens zwei Fahrstreifen in einer Fahrtrichtung vorhanden sein"},{"Text":"Die Fahrstreifen müssen durch Leitlinien markiert sein"},{"Text":"In der Fahrbahnmitte muss eine doppelte Sperrlinie vorhanden sein"},{"Text":"Kolonnenverkehr auf beiden Fahrstreifen"}],"en":[{"Text":"There must be at least two lanes going in one direction"},{"Text":"The lanes must be marked by broken lines"},{"Text":"There must be a double solid line between the lanes"},{"Text":"Moving columns of traffic in both lanes"}],"hr":[{"Text":"Moraju postojati najmanje dvije prometne trake u jednom smjeru vožnje"},{"Text":"Prometne trake moraju biti označene uzdužnim isprekidanim crtama"},{"Text":"Na sredini kolnika mora postojati dvostruka uzdužna puna crta"},{"Text":"Promet u kolonama na obje prometne trake"}],"sl":[{"Text":"Biti morata najmanj dva vozna pasova v eno smer"},{"Text":"Vozni pasovi morajo biti označeni s prekinjeno črto"},{"Text":"Na sredini vozišča mora biti dvojna neprekinjena črta"},{"Text":"Sklenjene kolone vozil na obeh voznih pasovih"}],"tr":[{"Text":"Aynı istikamette en az iki şerit olması gerekir"},{"Text":"Şeritlerin kesik çizgilerle ayrılmış olması gerekir"},{"Text":"Yolun ortasında çift duvar çizgi olmalıdır"},{"Text":"Her iki şeritte de konvoy oluşmuşsa"}]},"AntwortRichtig":[true,false,false,true]}